MANIFEST.in
README.md
settings.ini
setup.py
oceano_algos/__init__.py
oceano_algos/_nbdev.py
oceano_algos/core.py
oceano_algos/hh_parser.py
oceano_algos/kraken.py
oceano_algos/notificator.py
oceano_algos/parser.py
oceano_algos/postgres.py
oceano_algos/texts.py
oceano_algos.egg-info/PKG-INFO
oceano_algos.egg-info/SOURCES.txt
oceano_algos.egg-info/dependency_links.txt
oceano_algos.egg-info/requires.txt
oceano_algos.egg-info/top_level.txt