Metadata-Version: 2.1
Name: oceano-algos
Version: 0.0.190
Summary: A description of your project
Requires-Dist: pandas
Requires-Dist: fastcore
Requires-Dist: sqlalchemy==1.4.46
Requires-Dist: sshtunnel==0.4.0
Requires-Dist: loguru
Requires-Dist: psycopg2-binary
Requires-Dist: oceano-algos
Requires-Dist: selenium
Requires-Dist: beautifulsoup4
Requires-Dist: numpy
Requires-Dist: tqdm
Requires-Dist: psutil
Requires-Dist: boltons
Requires-Dist: pytelegrambotapi==4.10.0
Requires-Dist: pymystem3==0.2.0
Requires-Dist: scikit-learn==1.0.2
Requires-Dist: cryptocode
Requires-Dist: yoomoney
Requires-Dist: ccxt==4.0.102
